{
 "data": [
  {
   "name": "Topic0",
   "id": "t0",
   "values": [
    {
     "line": "1",
     "frequency": "0.011171387"
    },
    {
     "line": "2",
     "frequency": "0.0017059504"
    },
    {
     "line": "3",
     "frequency": "0"
    },
    {
     "line": "4",
     "frequency": "0.025655141"
    },
    {
     "line": "5",
     "frequency": "0"
    },
    {
     "line": "6",
     "frequency": "0.014483754"
    },
    {
     "line": "7",
     "frequency": "0"
    },
    {
     "line": "8",
     "frequency": "0"
    },
    {
     "line": "9",
     "frequency": "0"
    },
    {
     "line": "10",
     "frequency": "0"
    },
    {
     "line": "11",
     "frequency": "0"
    },
    {
     "line": "12",
     "frequency": "0"
    },
    {
     "line": "13",
     "frequency": "0"
    },
    {
     "line": "14",
     "frequency": "0"
    },
    {
     "line": "15",
     "frequency": "0"
    },
    {
     "line": "16",
     "frequency": "0"
    },
    {
     "line": "17",
     "frequency": "0"
    },
    {
     "line": "18",
     "frequency": "0"
    },
    {
     "line": "19",
     "frequency": "0"
    }
   ]
  },
  {
   "name": "Topic1",
   "id": "t1",
   "values": [
    {
     "line": "1",
     "frequency": "0"
    },
    {
     "line": "2",
     "frequency": "0"
    },
    {
     "line": "3",
     "frequency": "0"
    },
    {
     "line": "4",
     "frequency": "0"
    },
    {
     "line": "5",
     "frequency": "0"
    },
    {
     "line": "6",
     "frequency": "0"
    },
    {
     "line": "7",
     "frequency": "0"
    },
    {
     "line": "8",
     "frequency": "0"
    },
    {
     "line": "9",
     "frequency": "0"
    },
    {
     "line": "10",
     "frequency": "0"
    },
    {
     "line": "11",
     "frequency": "0"
    },
    {
     "line": "12",
     "frequency": "0"
    },
    {
     "line": "13",
     "frequency": "0"
    },
    {
     "line": "14",
     "frequency": "0.0028350104"
    },
    {
     "line": "15",
     "frequency": "0"
    },
    {
     "line": "16",
     "frequency": "0"
    },
    {
     "line": "17",
     "frequency": "0"
    },
    {
     "line": "18",
     "frequency": "0"
    },
    {
     "line": "19",
     "frequency": "0"
    }
   ]
  },
  {
   "name": "Topic2",
   "id": "t2",
   "values": [
    {
     "line": "1",
     "frequency": "0"
    },
    {
     "line": "2",
     "frequency": "0.0067577027"
    },
    {
     "line": "3",
     "frequency": "0"
    },
    {
     "line": "4",
     "frequency": "0"
    },
    {
     "line": "5",
     "frequency": "0"
    },
    {
     "line": "6",
     "frequency": "0"
    },
    {
     "line": "7",
     "frequency": "0"
    },
    {
     "line": "8",
     "frequency": "0"
    },
    {
     "line": "9",
     "frequency": "0"
    },
    {
     "line": "10",
     "frequency": "0"
    },
    {
     "line": "11",
     "frequency": "0"
    },
    {
     "line": "12",
     "frequency": "0"
    },
    {
     "line": "13",
     "frequency": "0"
    },
    {
     "line": "14",
     "frequency": "0.0035153772"
    },
    {
     "line": "15",
     "frequency": "0"
    },
    {
     "line": "16",
     "frequency": "0"
    },
    {
     "line": "17",
     "frequency": "0"
    },
    {
     "line": "18",
     "frequency": "0"
    },
    {
     "line": "19",
     "frequency": "0"
    }
   ]
  },
  {
   "name": "Topic3",
   "id": "t3",
   "values": [
    {
     "line": "1",
     "frequency": "0"
    },
    {
     "line": "2",
     "frequency": "0.008280188"
    },
    {
     "line": "3",
     "frequency": "0.0151306205"
    },
    {
     "line": "4",
     "frequency": "0"
    },
    {
     "line": "5",
     "frequency": "0"
    },
    {
     "line": "6",
     "frequency": "0"
    },
    {
     "line": "7",
     "frequency": "0"
    },
    {
     "line": "8",
     "frequency": "0.0045517357"
    },
    {
     "line": "9",
     "frequency": "0"
    },
    {
     "line": "10",
     "frequency": "0"
    },
    {
     "line": "11",
     "frequency": "0.0045517357"
    },
    {
     "line": "12",
     "frequency": "0"
    },
    {
     "line": "13",
     "frequency": "0.0021429888"
    },
    {
     "line": "14",
     "frequency": "0"
    },
    {
     "line": "15",
     "frequency": "0"
    },
    {
     "line": "16",
     "frequency": "0"
    },
    {
     "line": "17",
     "frequency": "0"
    },
    {
     "line": "18",
     "frequency": "0.0021429888"
    },
    {
     "line": "19",
     "frequency": "0"
    }
   ]
  },
  {
   "name": "Topic4",
   "id": "t4",
   "values": [
    {
     "line": "1",
     "frequency": "0.0960086295"
    },
    {
     "line": "2",
     "frequency": "0.04828020239999999"
    },
    {
     "line": "3",
     "frequency": "0.0425815823"
    },
    {
     "line": "4",
     "frequency": "0.0667313737"
    },
    {
     "line": "5",
     "frequency": "0.0422685566"
    },
    {
     "line": "6",
     "frequency": "0.0544669594"
    },
    {
     "line": "7",
     "frequency": "0.0658335453"
    },
    {
     "line": "8",
     "frequency": "0.07119758400000001"
    },
    {
     "line": "9",
     "frequency": "0.042218528000000005"
    },
    {
     "line": "10",
     "frequency": "0.0363025054"
    },
    {
     "line": "11",
     "frequency": "0.048209027700000004"
    },
    {
     "line": "12",
     "frequency": "0.0413296037"
    },
    {
     "line": "13",
     "frequency": "0.0295004044"
    },
    {
     "line": "14",
     "frequency": "0.0246360006"
    },
    {
     "line": "15",
     "frequency": "0.054108819399999994"
    },
    {
     "line": "16",
     "frequency": "0.0180074991"
    },
    {
     "line": "17",
     "frequency": "0.042281464500000004"
    },
    {
     "line": "18",
     "frequency": "0.034979118000000003"
    },
    {
     "line": "19",
     "frequency": "0.0183161163"
    }
   ]
  },
  {
   "name": "Topic5",
   "id": "t5",
   "values": [
    {
     "line": "1",
     "frequency": "0"
    },
    {
     "line": "2",
     "frequency": "0.003234104"
    },
    {
     "line": "3",
     "frequency": "0"
    },
    {
     "line": "4",
     "frequency": "0.011421495"
    },
    {
     "line": "5",
     "frequency": "0"
    },
    {
     "line": "6",
     "frequency": "0.011421495"
    },
    {
     "line": "7",
     "frequency": "0"
    },
    {
     "line": "8",
     "frequency": "0"
    },
    {
     "line": "9",
     "frequency": "0"
    },
    {
     "line": "10",
     "frequency": "0"
    },
    {
     "line": "11",
     "frequency": "0"
    },
    {
     "line": "12",
     "frequency": "0"
    },
    {
     "line": "13",
     "frequency": "0"
    },
    {
     "line": "14",
     "frequency": "0"
    },
    {
     "line": "15",
     "frequency": "0"
    },
    {
     "line": "16",
     "frequency": "0"
    },
    {
     "line": "17",
     "frequency": "0"
    },
    {
     "line": "18",
     "frequency": "0"
    },
    {
     "line": "19",
     "frequency": "0"
    }
   ]
  },
  {
   "name": "Topic6",
   "id": "t6",
   "values": [
    {
     "line": "1",
     "frequency": "0.0032353338"
    },
    {
     "line": "2",
     "frequency": "0.0030483464"
    },
    {
     "line": "3",
     "frequency": "0.004630214"
    },
    {
     "line": "4",
     "frequency": "0.002785281"
    },
    {
     "line": "5",
     "frequency": "0"
    },
    {
     "line": "6",
     "frequency": "0"
    },
    {
     "line": "7",
     "frequency": "0.0032638155"
    },
    {
     "line": "8",
     "frequency": "0"
    },
    {
     "line": "9",
     "frequency": "0.0032638155"
    },
    {
     "line": "10",
     "frequency": "0.0032353338"
    },
    {
     "line": "11",
     "frequency": "0"
    },
    {
     "line": "12",
     "frequency": "0"
    },
    {
     "line": "13",
     "frequency": "0.0027124544"
    },
    {
     "line": "14",
     "frequency": "0.0026320734"
    },
    {
     "line": "15",
     "frequency": "0"
    },
    {
     "line": "16",
     "frequency": "0"
    },
    {
     "line": "17",
     "frequency": "0.0032638155"
    },
    {
     "line": "18",
     "frequency": "0.0027124544"
    },
    {
     "line": "19",
     "frequency": "0"
    }
   ]
  },
  {
   "name": "Topic7",
   "id": "t7",
   "values": [
    {
     "line": "1",
     "frequency": "0"
    },
    {
     "line": "2",
     "frequency": "0"
    },
    {
     "line": "3",
     "frequency": "0"
    },
    {
     "line": "4",
     "frequency": "0"
    },
    {
     "line": "5",
     "frequency": "0"
    },
    {
     "line": "6",
     "frequency": "0"
    },
    {
     "line": "7",
     "frequency": "0.0029546076"
    },
    {
     "line": "8",
     "frequency": "0"
    },
    {
     "line": "9",
     "frequency": "0.0029546076"
    },
    {
     "line": "10",
     "frequency": "0"
    },
    {
     "line": "11",
     "frequency": "0"
    },
    {
     "line": "12",
     "frequency": "0"
    },
    {
     "line": "13",
     "frequency": "0"
    },
    {
     "line": "14",
     "frequency": "0"
    },
    {
     "line": "15",
     "frequency": "0"
    },
    {
     "line": "16",
     "frequency": "0"
    },
    {
     "line": "17",
     "frequency": "0.0029546076"
    },
    {
     "line": "18",
     "frequency": "0"
    },
    {
     "line": "19",
     "frequency": "0"
    }
   ]
  },
  {
   "name": "Topic8",
   "id": "t8",
   "values": [
    {
     "line": "1",
     "frequency": "0.0147259868"
    },
    {
     "line": "2",
     "frequency": "0"
    },
    {
     "line": "3",
     "frequency": "0.004394812"
    },
    {
     "line": "4",
     "frequency": "0.0161455943"
    },
    {
     "line": "5",
     "frequency": "0.004394812"
    },
    {
     "line": "6",
     "frequency": "0.007343918"
    },
    {
     "line": "7",
     "frequency": "0"
    },
    {
     "line": "8",
     "frequency": "0"
    },
    {
     "line": "9",
     "frequency": "0"
    },
    {
     "line": "10",
     "frequency": "0.0065870592"
    },
    {
     "line": "11",
     "frequency": "0"
    },
    {
     "line": "12",
     "frequency": "0"
    },
    {
     "line": "13",
     "frequency": "0.0042028087"
    },
    {
     "line": "14",
     "frequency": "0"
    },
    {
     "line": "15",
     "frequency": "0"
    },
    {
     "line": "16",
     "frequency": "0"
    },
    {
     "line": "17",
     "frequency": "0"
    },
    {
     "line": "18",
     "frequency": "0.0042028087"
    },
    {
     "line": "19",
     "frequency": "0"
    }
   ]
  },
  {
   "name": "Topic9",
   "id": "t9",
   "values": [
    {
     "line": "1",
     "frequency": "0.0021684018"
    },
    {
     "line": "2",
     "frequency": "0.0018905617"
    },
    {
     "line": "3",
     "frequency": "0.0101363833"
    },
    {
     "line": "4",
     "frequency": "0.0061811157999999995"
    },
    {
     "line": "5",
     "frequency": "0"
    },
    {
     "line": "6",
     "frequency": "0.004012714"
    },
    {
     "line": "7",
     "frequency": "0.0017362968"
    },
    {
     "line": "8",
     "frequency": "0"
    },
    {
     "line": "9",
     "frequency": "0.0017362968"
    },
    {
     "line": "10",
     "frequency": "0"
    },
    {
     "line": "11",
     "frequency": "0"
    },
    {
     "line": "12",
     "frequency": "0"
    },
    {
     "line": "13",
     "frequency": "0"
    },
    {
     "line": "14",
     "frequency": "0.0015735263"
    },
    {
     "line": "15",
     "frequency": "0"
    },
    {
     "line": "16",
     "frequency": "0"
    },
    {
     "line": "17",
     "frequency": "0.0017362968"
    },
    {
     "line": "18",
     "frequency": "0"
    },
    {
     "line": "19",
     "frequency": "0"
    }
   ]
  },
  {
   "name": "Topic10",
   "id": "t10",
   "values": [
    {
     "line": "1",
     "frequency": "0"
    },
    {
     "line": "2",
     "frequency": "0.0045539318"
    },
    {
     "line": "3",
     "frequency": "0.0033883997"
    },
    {
     "line": "4",
     "frequency": "0"
    },
    {
     "line": "5",
     "frequency": "0"
    },
    {
     "line": "6",
     "frequency": "0"
    },
    {
     "line": "7",
     "frequency": "0"
    },
    {
     "line": "8",
     "frequency": "0"
    },
    {
     "line": "9",
     "frequency": "0"
    },
    {
     "line": "10",
     "frequency": "0"
    },
    {
     "line": "11",
     "frequency": "0"
    },
    {
     "line": "12",
     "frequency": "0"
    },
    {
     "line": "13",
     "frequency": "0"
    },
    {
     "line": "14",
     "frequency": "0.0053759236"
    },
    {
     "line": "15",
     "frequency": "0"
    },
    {
     "line": "16",
     "frequency": "0"
    },
    {
     "line": "17",
     "frequency": "0"
    },
    {
     "line": "18",
     "frequency": "0"
    },
    {
     "line": "19",
     "frequency": "0"
    }
   ]
  },
  {
   "name": "Topic11",
   "id": "t11",
   "values": [
    {
     "line": "1",
     "frequency": "0"
    },
    {
     "line": "2",
     "frequency": "0"
    },
    {
     "line": "3",
     "frequency": "0"
    },
    {
     "line": "4",
     "frequency": "0"
    },
    {
     "line": "5",
     "frequency": "0"
    },
    {
     "line": "6",
     "frequency": "0"
    },
    {
     "line": "7",
     "frequency": "0"
    },
    {
     "line": "8",
     "frequency": "0"
    },
    {
     "line": "9",
     "frequency": "0"
    },
    {
     "line": "10",
     "frequency": "0"
    },
    {
     "line": "11",
     "frequency": "0"
    },
    {
     "line": "12",
     "frequency": "0"
    },
    {
     "line": "13",
     "frequency": "0"
    },
    {
     "line": "14",
     "frequency": "0"
    },
    {
     "line": "15",
     "frequency": "0"
    },
    {
     "line": "16",
     "frequency": "0"
    },
    {
     "line": "17",
     "frequency": "0"
    },
    {
     "line": "18",
     "frequency": "0"
    },
    {
     "line": "19",
     "frequency": "0"
    }
   ]
  },
  {
   "name": "Topic12",
   "id": "t12",
   "values": [
    {
     "line": "1",
     "frequency": "0.0022499503"
    },
    {
     "line": "2",
     "frequency": "0.004290494"
    },
    {
     "line": "3",
     "frequency": "0"
    },
    {
     "line": "4",
     "frequency": "0.0022499503"
    },
    {
     "line": "5",
     "frequency": "0"
    },
    {
     "line": "6",
     "frequency": "0.0022499503"
    },
    {
     "line": "7",
     "frequency": "0"
    },
    {
     "line": "8",
     "frequency": "0"
    },
    {
     "line": "9",
     "frequency": "0"
    },
    {
     "line": "10",
     "frequency": "0"
    },
    {
     "line": "11",
     "frequency": "0"
    },
    {
     "line": "12",
     "frequency": "0"
    },
    {
     "line": "13",
     "frequency": "0"
    },
    {
     "line": "14",
     "frequency": "0.0059655258"
    },
    {
     "line": "15",
     "frequency": "0"
    },
    {
     "line": "16",
     "frequency": "0"
    },
    {
     "line": "17",
     "frequency": "0"
    },
    {
     "line": "18",
     "frequency": "0"
    },
    {
     "line": "19",
     "frequency": "0"
    }
   ]
  },
  {
   "name": "Topic13",
   "id": "t13",
   "values": [
    {
     "line": "1",
     "frequency": "0"
    },
    {
     "line": "2",
     "frequency": "0.0016317938"
    },
    {
     "line": "3",
     "frequency": "0"
    },
    {
     "line": "4",
     "frequency": "0"
    },
    {
     "line": "5",
     "frequency": "0"
    },
    {
     "line": "6",
     "frequency": "0"
    },
    {
     "line": "7",
     "frequency": "0"
    },
    {
     "line": "8",
     "frequency": "0"
    },
    {
     "line": "9",
     "frequency": "0"
    },
    {
     "line": "10",
     "frequency": "0"
    },
    {
     "line": "11",
     "frequency": "0"
    },
    {
     "line": "12",
     "frequency": "0"
    },
    {
     "line": "13",
     "frequency": "0"
    },
    {
     "line": "14",
     "frequency": "0"
    },
    {
     "line": "15",
     "frequency": "0"
    },
    {
     "line": "16",
     "frequency": "0"
    },
    {
     "line": "17",
     "frequency": "0"
    },
    {
     "line": "18",
     "frequency": "0"
    },
    {
     "line": "19",
     "frequency": "0"
    }
   ]
  },
  {
   "name": "Topic14",
   "id": "t14",
   "values": [
    {
     "line": "1",
     "frequency": "0.021288654"
    },
    {
     "line": "2",
     "frequency": "0.0026837853"
    },
    {
     "line": "3",
     "frequency": "0.00632235"
    },
    {
     "line": "4",
     "frequency": "0.0171467983"
    },
    {
     "line": "5",
     "frequency": "0.00632235"
    },
    {
     "line": "6",
     "frequency": "0.0068248063"
    },
    {
     "line": "7",
     "frequency": "0"
    },
    {
     "line": "8",
     "frequency": "0"
    },
    {
     "line": "9",
     "frequency": "0"
    },
    {
     "line": "10",
     "frequency": "0.010431111"
    },
    {
     "line": "11",
     "frequency": "0"
    },
    {
     "line": "12",
     "frequency": "0"
    },
    {
     "line": "13",
     "frequency": "0.0051436825"
    },
    {
     "line": "14",
     "frequency": "0"
    },
    {
     "line": "15",
     "frequency": "0"
    },
    {
     "line": "16",
     "frequency": "0"
    },
    {
     "line": "17",
     "frequency": "0"
    },
    {
     "line": "18",
     "frequency": "0.0051436825"
    },
    {
     "line": "19",
     "frequency": "0"
    }
   ]
  },
  {
   "name": "Topic15",
   "id": "t15",
   "values": [
    {
     "line": "1",
     "frequency": "0.0025392754"
    },
    {
     "line": "2",
     "frequency": "0.0026089929"
    },
    {
     "line": "3",
     "frequency": "0"
    },
    {
     "line": "4",
     "frequency": "0.0073925291"
    },
    {
     "line": "5",
     "frequency": "0"
    },
    {
     "line": "6",
     "frequency": "0.0073925291"
    },
    {
     "line": "7",
     "frequency": "0"
    },
    {
     "line": "8",
     "frequency": "0"
    },
    {
     "line": "9",
     "frequency": "0"
    },
    {
     "line": "10",
     "frequency": "0"
    },
    {
     "line": "11",
     "frequency": "0"
    },
    {
     "line": "12",
     "frequency": "0"
    },
    {
     "line": "13",
     "frequency": "0"
    },
    {
     "line": "14",
     "frequency": "0.009658079"
    },
    {
     "line": "15",
     "frequency": "0"
    },
    {
     "line": "16",
     "frequency": "0.0033031267"
    },
    {
     "line": "17",
     "frequency": "0"
    },
    {
     "line": "18",
     "frequency": "0"
    },
    {
     "line": "19",
     "frequency": "0"
    }
   ]
  },
  {
   "name": "Topic16",
   "id": "t16",
   "values": [
    {
     "line": "1",
     "frequency": "0"
    },
    {
     "line": "2",
     "frequency": "0"
    },
    {
     "line": "3",
     "frequency": "0"
    },
    {
     "line": "4",
     "frequency": "0"
    },
    {
     "line": "5",
     "frequency": "0"
    },
    {
     "line": "6",
     "frequency": "0"
    },
    {
     "line": "7",
     "frequency": "0"
    },
    {
     "line": "8",
     "frequency": "0"
    },
    {
     "line": "9",
     "frequency": "0"
    },
    {
     "line": "10",
     "frequency": "0"
    },
    {
     "line": "11",
     "frequency": "0"
    },
    {
     "line": "12",
     "frequency": "0"
    },
    {
     "line": "13",
     "frequency": "0"
    },
    {
     "line": "14",
     "frequency": "0.0036667902"
    },
    {
     "line": "15",
     "frequency": "0"
    },
    {
     "line": "16",
     "frequency": "0"
    },
    {
     "line": "17",
     "frequency": "0"
    },
    {
     "line": "18",
     "frequency": "0"
    },
    {
     "line": "19",
     "frequency": "0"
    }
   ]
  },
  {
   "name": "Topic17",
   "id": "t17",
   "values": [
    {
     "line": "1",
     "frequency": "0"
    },
    {
     "line": "2",
     "frequency": "0"
    },
    {
     "line": "3",
     "frequency": "0"
    },
    {
     "line": "4",
     "frequency": "0"
    },
    {
     "line": "5",
     "frequency": "0"
    },
    {
     "line": "6",
     "frequency": "0"
    },
    {
     "line": "7",
     "frequency": "0.0032528145"
    },
    {
     "line": "8",
     "frequency": "0"
    },
    {
     "line": "9",
     "frequency": "0.0032528145"
    },
    {
     "line": "10",
     "frequency": "0"
    },
    {
     "line": "11",
     "frequency": "0"
    },
    {
     "line": "12",
     "frequency": "0"
    },
    {
     "line": "13",
     "frequency": "0"
    },
    {
     "line": "14",
     "frequency": "0.004609418"
    },
    {
     "line": "15",
     "frequency": "0"
    },
    {
     "line": "16",
     "frequency": "0"
    },
    {
     "line": "17",
     "frequency": "0.0032528145"
    },
    {
     "line": "18",
     "frequency": "0"
    },
    {
     "line": "19",
     "frequency": "0"
    }
   ]
  },
  {
   "name": "Topic18",
   "id": "t18",
   "values": [
    {
     "line": "1",
     "frequency": "0.017208684"
    },
    {
     "line": "2",
     "frequency": "0.008279283"
    },
    {
     "line": "3",
     "frequency": "0.007750862"
    },
    {
     "line": "4",
     "frequency": "0.005945096"
    },
    {
     "line": "5",
     "frequency": "0.007750862"
    },
    {
     "line": "6",
     "frequency": "0"
    },
    {
     "line": "7",
     "frequency": "0"
    },
    {
     "line": "8",
     "frequency": "0"
    },
    {
     "line": "9",
     "frequency": "0"
    },
    {
     "line": "10",
     "frequency": "0.009457822"
    },
    {
     "line": "11",
     "frequency": "0"
    },
    {
     "line": "12",
     "frequency": "0"
    },
    {
     "line": "13",
     "frequency": "0.0076478343"
    },
    {
     "line": "14",
     "frequency": "0"
    },
    {
     "line": "15",
     "frequency": "0"
    },
    {
     "line": "16",
     "frequency": "0"
    },
    {
     "line": "17",
     "frequency": "0"
    },
    {
     "line": "18",
     "frequency": "0.0076478343"
    },
    {
     "line": "19",
     "frequency": "0"
    }
   ]
  },
  {
   "name": "Topic19",
   "id": "t19",
   "values": [
    {
     "line": "1",
     "frequency": "0"
    },
    {
     "line": "2",
     "frequency": "0.0060416725"
    },
    {
     "line": "3",
     "frequency": "0.0034687987"
    },
    {
     "line": "4",
     "frequency": "0.00396652"
    },
    {
     "line": "5",
     "frequency": "0"
    },
    {
     "line": "6",
     "frequency": "0.00396652"
    },
    {
     "line": "7",
     "frequency": "0.004546884"
    },
    {
     "line": "8",
     "frequency": "0"
    },
    {
     "line": "9",
     "frequency": "0.004546884"
    },
    {
     "line": "10",
     "frequency": "0"
    },
    {
     "line": "11",
     "frequency": "0"
    },
    {
     "line": "12",
     "frequency": "0"
    },
    {
     "line": "13",
     "frequency": "0"
    },
    {
     "line": "14",
     "frequency": "0"
    },
    {
     "line": "15",
     "frequency": "0"
    },
    {
     "line": "16",
     "frequency": "0"
    },
    {
     "line": "17",
     "frequency": "0.004546884"
    },
    {
     "line": "18",
     "frequency": "0"
    },
    {
     "line": "19",
     "frequency": "0"
    }
   ]
  },
  {
   "name": "Topic20",
   "id": "t20",
   "values": [
    {
     "line": "1",
     "frequency": "0"
    },
    {
     "line": "2",
     "frequency": "0.009165305"
    },
    {
     "line": "3",
     "frequency": "0.0033658836"
    },
    {
     "line": "4",
     "frequency": "0"
    },
    {
     "line": "5",
     "frequency": "0"
    },
    {
     "line": "6",
     "frequency": "0"
    },
    {
     "line": "7",
     "frequency": "0.0029994058"
    },
    {
     "line": "8",
     "frequency": "0"
    },
    {
     "line": "9",
     "frequency": "0.0029994058"
    },
    {
     "line": "10",
     "frequency": "0"
    },
    {
     "line": "11",
     "frequency": "0"
    },
    {
     "line": "12",
     "frequency": "0"
    },
    {
     "line": "13",
     "frequency": "0"
    },
    {
     "line": "14",
     "frequency": "0"
    },
    {
     "line": "15",
     "frequency": "0"
    },
    {
     "line": "16",
     "frequency": "0"
    },
    {
     "line": "17",
     "frequency": "0.0029994058"
    },
    {
     "line": "18",
     "frequency": "0"
    },
    {
     "line": "19",
     "frequency": "0"
    }
   ]
  },
  {
   "name": "Topic21",
   "id": "t21",
   "values": [
    {
     "line": "1",
     "frequency": "0.0170653129"
    },
    {
     "line": "2",
     "frequency": "0.0165485392"
    },
    {
     "line": "3",
     "frequency": "0.0089541462"
    },
    {
     "line": "4",
     "frequency": "0.0069967818"
    },
    {
     "line": "5",
     "frequency": "0.0063445317"
    },
    {
     "line": "6",
     "frequency": "0.008495456299999999"
    },
    {
     "line": "7",
     "frequency": "0.0087039601"
    },
    {
     "line": "8",
     "frequency": "0.015251870499999999"
    },
    {
     "line": "9",
     "frequency": "0.006164084"
    },
    {
     "line": "10",
     "frequency": "0.0048745374"
    },
    {
     "line": "11",
     "frequency": "0.0086650003"
    },
    {
     "line": "12",
     "frequency": "0.0051538884"
    },
    {
     "line": "13",
     "frequency": "0.004378019"
    },
    {
     "line": "14",
     "frequency": "0"
    },
    {
     "line": "15",
     "frequency": "0.008043752500000001"
    },
    {
     "line": "16",
     "frequency": "0"
    },
    {
     "line": "17",
     "frequency": "0.0034693496"
    },
    {
     "line": "18",
     "frequency": "0.011564143"
    },
    {
     "line": "19",
     "frequency": "0"
    }
   ]
  },
  {
   "name": "Topic22",
   "id": "t22",
   "values": [
    {
     "line": "1",
     "frequency": "0"
    },
    {
     "line": "2",
     "frequency": "0"
    },
    {
     "line": "3",
     "frequency": "0"
    },
    {
     "line": "4",
     "frequency": "0"
    },
    {
     "line": "5",
     "frequency": "0"
    },
    {
     "line": "6",
     "frequency": "0"
    },
    {
     "line": "7",
     "frequency": "0"
    },
    {
     "line": "8",
     "frequency": "0"
    },
    {
     "line": "9",
     "frequency": "0"
    },
    {
     "line": "10",
     "frequency": "0"
    },
    {
     "line": "11",
     "frequency": "0"
    },
    {
     "line": "12",
     "frequency": "0"
    },
    {
     "line": "13",
     "frequency": "0"
    },
    {
     "line": "14",
     "frequency": "0"
    },
    {
     "line": "15",
     "frequency": "0"
    },
    {
     "line": "16",
     "frequency": "0"
    },
    {
     "line": "17",
     "frequency": "0"
    },
    {
     "line": "18",
     "frequency": "0"
    },
    {
     "line": "19",
     "frequency": "0"
    }
   ]
  },
  {
   "name": "Topic23",
   "id": "t23",
   "values": [
    {
     "line": "1",
     "frequency": "0"
    },
    {
     "line": "2",
     "frequency": "0.011733904"
    },
    {
     "line": "3",
     "frequency": "0.011255863999999999"
    },
    {
     "line": "4",
     "frequency": "0.008262481"
    },
    {
     "line": "5",
     "frequency": "0"
    },
    {
     "line": "6",
     "frequency": "0.008262481"
    },
    {
     "line": "7",
     "frequency": "0"
    },
    {
     "line": "8",
     "frequency": "0"
    },
    {
     "line": "9",
     "frequency": "0"
    },
    {
     "line": "10",
     "frequency": "0"
    },
    {
     "line": "11",
     "frequency": "0"
    },
    {
     "line": "12",
     "frequency": "0"
    },
    {
     "line": "13",
     "frequency": "0"
    },
    {
     "line": "14",
     "frequency": "0"
    },
    {
     "line": "15",
     "frequency": "0"
    },
    {
     "line": "16",
     "frequency": "0"
    },
    {
     "line": "17",
     "frequency": "0"
    },
    {
     "line": "18",
     "frequency": "0"
    },
    {
     "line": "19",
     "frequency": "0"
    }
   ]
  },
  {
   "name": "Topic24",
   "id": "t24",
   "values": [
    {
     "line": "1",
     "frequency": "0"
    },
    {
     "line": "2",
     "frequency": "0.0059217624"
    },
    {
     "line": "3",
     "frequency": "0.0054104943"
    },
    {
     "line": "4",
     "frequency": "0"
    },
    {
     "line": "5",
     "frequency": "0"
    },
    {
     "line": "6",
     "frequency": "0"
    },
    {
     "line": "7",
     "frequency": "0"
    },
    {
     "line": "8",
     "frequency": "0.0064744972"
    },
    {
     "line": "9",
     "frequency": "0"
    },
    {
     "line": "10",
     "frequency": "0"
    },
    {
     "line": "11",
     "frequency": "0.0032372486"
    },
    {
     "line": "12",
     "frequency": "0"
    },
    {
     "line": "13",
     "frequency": "0"
    },
    {
     "line": "14",
     "frequency": "0.0028948027"
    },
    {
     "line": "15",
     "frequency": "0"
    },
    {
     "line": "16",
     "frequency": "0"
    },
    {
     "line": "17",
     "frequency": "0"
    },
    {
     "line": "18",
     "frequency": "0"
    },
    {
     "line": "19",
     "frequency": "0"
    }
   ]
  },
  {
   "name": "Topic25",
   "id": "t25",
   "values": [
    {
     "line": "1",
     "frequency": "0"
    },
    {
     "line": "2",
     "frequency": "0"
    },
    {
     "line": "3",
     "frequency": "0"
    },
    {
     "line": "4",
     "frequency": "0"
    },
    {
     "line": "5",
     "frequency": "0"
    },
    {
     "line": "6",
     "frequency": "0"
    },
    {
     "line": "7",
     "frequency": "0"
    },
    {
     "line": "8",
     "frequency": "0"
    },
    {
     "line": "9",
     "frequency": "0"
    },
    {
     "line": "10",
     "frequency": "0"
    },
    {
     "line": "11",
     "frequency": "0"
    },
    {
     "line": "12",
     "frequency": "0"
    },
    {
     "line": "13",
     "frequency": "0"
    },
    {
     "line": "14",
     "frequency": "0"
    },
    {
     "line": "15",
     "frequency": "0"
    },
    {
     "line": "16",
     "frequency": "0"
    },
    {
     "line": "17",
     "frequency": "0"
    },
    {
     "line": "18",
     "frequency": "0"
    },
    {
     "line": "19",
     "frequency": "0"
    }
   ]
  },
  {
   "name": "Topic26",
   "id": "t26",
   "values": [
    {
     "line": "1",
     "frequency": "0"
    },
    {
     "line": "2",
     "frequency": "0"
    },
    {
     "line": "3",
     "frequency": "0"
    },
    {
     "line": "4",
     "frequency": "0"
    },
    {
     "line": "5",
     "frequency": "0"
    },
    {
     "line": "6",
     "frequency": "0"
    },
    {
     "line": "7",
     "frequency": "0"
    },
    {
     "line": "8",
     "frequency": "0"
    },
    {
     "line": "9",
     "frequency": "0"
    },
    {
     "line": "10",
     "frequency": "0"
    },
    {
     "line": "11",
     "frequency": "0"
    },
    {
     "line": "12",
     "frequency": "0"
    },
    {
     "line": "13",
     "frequency": "0"
    },
    {
     "line": "14",
     "frequency": "0.0018437888"
    },
    {
     "line": "15",
     "frequency": "0"
    },
    {
     "line": "16",
     "frequency": "0"
    },
    {
     "line": "17",
     "frequency": "0"
    },
    {
     "line": "18",
     "frequency": "0"
    },
    {
     "line": "19",
     "frequency": "0"
    }
   ]
  },
  {
   "name": "Topic27",
   "id": "t27",
   "values": [
    {
     "line": "1",
     "frequency": "0"
    },
    {
     "line": "2",
     "frequency": "0.00489439"
    },
    {
     "line": "3",
     "frequency": "0"
    },
    {
     "line": "4",
     "frequency": "0"
    },
    {
     "line": "5",
     "frequency": "0"
    },
    {
     "line": "6",
     "frequency": "0"
    },
    {
     "line": "7",
     "frequency": "0"
    },
    {
     "line": "8",
     "frequency": "0"
    },
    {
     "line": "9",
     "frequency": "0"
    },
    {
     "line": "10",
     "frequency": "0"
    },
    {
     "line": "11",
     "frequency": "0"
    },
    {
     "line": "12",
     "frequency": "0"
    },
    {
     "line": "13",
     "frequency": "0"
    },
    {
     "line": "14",
     "frequency": "0"
    },
    {
     "line": "15",
     "frequency": "0"
    },
    {
     "line": "16",
     "frequency": "0"
    },
    {
     "line": "17",
     "frequency": "0"
    },
    {
     "line": "18",
     "frequency": "0"
    },
    {
     "line": "19",
     "frequency": "0"
    }
   ]
  },
  {
   "name": "Topic28",
   "id": "t28",
   "values": [
    {
     "line": "1",
     "frequency": "0"
    },
    {
     "line": "2",
     "frequency": "0.0042710425"
    },
    {
     "line": "3",
     "frequency": "0"
    },
    {
     "line": "4",
     "frequency": "0"
    },
    {
     "line": "5",
     "frequency": "0"
    },
    {
     "line": "6",
     "frequency": "0"
    },
    {
     "line": "7",
     "frequency": "0"
    },
    {
     "line": "8",
     "frequency": "0"
    },
    {
     "line": "9",
     "frequency": "0"
    },
    {
     "line": "10",
     "frequency": "0"
    },
    {
     "line": "11",
     "frequency": "0"
    },
    {
     "line": "12",
     "frequency": "0"
    },
    {
     "line": "13",
     "frequency": "0"
    },
    {
     "line": "14",
     "frequency": "0"
    },
    {
     "line": "15",
     "frequency": "0"
    },
    {
     "line": "16",
     "frequency": "0"
    },
    {
     "line": "17",
     "frequency": "0"
    },
    {
     "line": "18",
     "frequency": "0"
    },
    {
     "line": "19",
     "frequency": "0"
    }
   ]
  },
  {
   "name": "Topic29",
   "id": "t29",
   "values": [
    {
     "line": "1",
     "frequency": "0"
    },
    {
     "line": "2",
     "frequency": "0.0049479213"
    },
    {
     "line": "3",
     "frequency": "0.0030263886"
    },
    {
     "line": "4",
     "frequency": "0"
    },
    {
     "line": "5",
     "frequency": "0"
    },
    {
     "line": "6",
     "frequency": "0"
    },
    {
     "line": "7",
     "frequency": "0"
    },
    {
     "line": "8",
     "frequency": "0.0057829028"
    },
    {
     "line": "9",
     "frequency": "0"
    },
    {
     "line": "10",
     "frequency": "0"
    },
    {
     "line": "11",
     "frequency": "0.0028914514"
    },
    {
     "line": "12",
     "frequency": "0"
    },
    {
     "line": "13",
     "frequency": "0"
    },
    {
     "line": "14",
     "frequency": "0"
    },
    {
     "line": "15",
     "frequency": "0"
    },
    {
     "line": "16",
     "frequency": "0"
    },
    {
     "line": "17",
     "frequency": "0"
    },
    {
     "line": "18",
     "frequency": "0"
    },
    {
     "line": "19",
     "frequency": "0"
    }
   ]
  }
 ]
}