{"data": [{"name": "Topic0", "id": "t0", "values": [{"line": 1, "frequency": 0.018246392020955682}]}, {"name": "Topic1", "id": "t1", "values": [{"line": 1, "frequency": 0.01955530361738056}]}, {"name": "Topic2", "id": "t2", "values": [{"line": 1, "frequency": 0.01741147751454264}]}, {"name": "Topic3", "id": "t3", "values": [{"line": 1, "frequency": 0.020016775000840425}]}, {"name": "Topic4", "id": "t4", "values": [{"line": 1, "frequency": 0.01869732839986682}]}, {"name": "Topic5", "id": "t5", "values": [{"line": 1, "frequency": 0.019269395270384848}]}, {"name": "Topic6", "id": "t6", "values": [{"line": 1, "frequency": 0.018306058715097606}]}, {"name": "Topic7", "id": "t7", "values": [{"line": 1, "frequency": 0.018969141878187656}]}, {"name": "Topic8", "id": "t8", "values": [{"line": 1, "frequency": 0.016907452489249408}]}, {"name": "Topic9", "id": "t9", "values": [{"line": 1, "frequency": 0.019215659238398075}]}, {"name": "Topic10", "id": "t10", "values": [{"line": 1, "frequency": 0.01709399209357798}]}, {"name": "Topic11", "id": "t11", "values": [{"line": 1, "frequency": 0.01815496734343469}]}, {"name": "Topic12", "id": "t12", "values": [{"line": 1, "frequency": 0.01661427493672818}]}, {"name": "Topic13", "id": "t13", "values": [{"line": 1, "frequency": 0.01773783832322806}]}, {"name": "Topic14", "id": "t14", "values": [{"line": 1, "frequency": 0.01866292324848473}]}, {"name": "Topic15", "id": "t15", "values": [{"line": 1, "frequency": 0.01871675276197493}]}, {"name": "Topic16", "id": "t16", "values": [{"line": 1, "frequency": 0.016655826242640615}]}, {"name": "Topic17", "id": "t17", "values": [{"line": 1, "frequency": 0.021896059741266072}]}, {"name": "Topic18", "id": "t18", "values": [{"line": 1, "frequency": 0.018071585334837437}]}, {"name": "Topic19", "id": "t19", "values": [{"line": 1, "frequency": 0.014957088395021856}]}, {"name": "Topic20", "id": "t20", "values": [{"line": 1, "frequency": 0.01617556973360479}]}, {"name": "Topic21", "id": "t21", "values": [{"line": 1, "frequency": 0.020398444845341146}]}, {"name": "Topic22", "id": "t22", "values": [{"line": 1, "frequency": 0.018678083433769643}]}, {"name": "Topic23", "id": "t23", "values": [{"line": 1, "frequency": 0.019333167118020356}]}, {"name": "Topic24", "id": "t24", "values": [{"line": 1, "frequency": 0.01997685176320374}]}, {"name": "Topic25", "id": "t25", "values": [{"line": 1, "frequency": 0.02092473767697811}]}, {"name": "Topic26", "id": "t26", "values": [{"line": 1, "frequency": 0.016921985894441605}]}, {"name": "Topic27", "id": "t27", "values": [{"line": 1, "frequency": 0.018731872434727848}]}, {"name": "Topic28", "id": "t28", "values": [{"line": 1, "frequency": 0.015229709795676172}]}, {"name": "Topic29", "id": "t29", "values": [{"line": 1, "frequency": 0.019752461928874254}]}]}